{
    "version": "47adca6",
    "description": "Lightning-fast and Powerful Code Editor written in Rust (nightly builds)",
    "homepage": "http://lapce.dev/",
    "license": "Apache-2.0",
    "architecture": {
        "64bit": {
            "url": "https://github.com/lapce/lapce/releases/download/nightly/Lapce-windows-portable.zip",
            "hash": "95dbf60c21e8001b9200b56088d6e04a26abbc3e5e3fe1e1dc1fa3c86992725d"
        }
    },
    "bin": [
        [
            "lapce.exe",
            "lapce-nightly"
        ]
    ],
    "shortcuts": [
        [
            "lapce.exe",
            "Lapce Nightly"
        ]
    ],
    "checkver": {
        "url": "https://github.com/lapce/lapce/releases/nightly",
        "regex": "href=\"\\/lapce\\/lapce\\/commit\\/([0-9a-f]{7})[0-9a-f]{33}\""
    },
    "autoupdate": {
        "architecture": {
            "64bit": {
                "url": "https://github.com/lapce/lapce/releases/download/nightly/Lapce-windows-portable.zip"
            }
        }
    }
}
