{
    "version": "nightly-3d921f6",
    "description": "Lightning-fast and Powerful Code Editor written in Rust (nightly builds)",
    "homepage": "http://lapce.dev/",
    "license": "Apache-2.0",
    "architecture": {
        "64bit": {
            "url": "https://github.com/lapce/lapce/releases/download/nightly/Lapce-windows-portable.zip",
            "hash": "75c24d8bea7397bcca1161a9663ec91476e691d7541141fbbe1b399429442c89"
        }
    },
    "bin": [
        [
            "lapce.exe",
            "lapce-nightly"
        ]
    ],
    "shortcuts": [
        [
            "lapce.exe",
            "Lapce Nightly"
        ]
    ],
    "persist": [
        [
            "lapce-data",
            "lapce-data"
        ]
    ],
    "checkver": {
        "url": "https://api.github.com/repos/lapce/lapce/releases",
        "jsonpath": "$.[?(@.tag_name == 'nightly')].target_commitish",
        "regex": "([\\w\\d]{7})[\\w\\d]+",
        "replace": "nightly-${1}"
    },
    "autoupdate": {
        "architecture": {
            "64bit": {
                "url": "https://github.com/lapce/lapce/releases/download/nightly/Lapce-windows-portable.zip"
            }
        }
    }
}
